restle/__init__.py
restle/actions.py
restle/exceptions.py
restle/fields.py
restle/options.py
restle/resources.py
restle/serializers.py
restle-0.5.1.dist-info/DESCRIPTION.rst
restle-0.5.1.dist-info/METADATA
restle-0.5.1.dist-info/RECORD
restle-0.5.1.dist-info/WHEEL
restle-0.5.1.dist-info/metadata.json
restle-0.5.1.dist-info/top_level.txt
