Metadata-Version: 2.0
Name: restle
Version: 0.5.1
Summary: A REST client framework
Home-page: https://github.com/consbio/restle
Author: UNKNOWN
Author-email: UNKNOWN
License: BSD
Keywords: rest,mapper,client
Platform: UNKNOWN
Requires: six
Requires: requests
